README.md
setup.py
pyswd.egg-info/PKG-INFO
pyswd.egg-info/SOURCES.txt
pyswd.egg-info/dependency_links.txt
pyswd.egg-info/entry_points.txt
pyswd.egg-info/requires.txt
pyswd.egg-info/top_level.txt
swd/__about__.py
swd/__init__.py
swd/_app.py
swd/cortexm.py
swd/swd.py
swd/stlink/__init__.py
swd/stlink/com.py
swd/stlink/usb.py
test/test_stlink.py
test/test_swd.py