Metadata-Version: 2.1
Name: pyswd
Version: 1.0.0
Summary: Is a python module for debugging microcontrollers with SWD using ST-Link/V2 (/V2-1) or V3 debugger. This package also contain small command line tool.
Home-page: https://github.com/pavelrevak/pyswd
Author: Pavel Revak
Author-email: pavel.revak@gmail.com
License: MIT
Keywords: SWD debugger STM32 STLINK CORTEX-M ARM
Platform: UNKNOWN
Classifier: Development Status :: 3 - Alpha
Classifier: Intended Audience :: Developers
Classifier: Topic :: Software Development :: Embedded Systems
Classifier: License :: OSI Approved :: MIT License
Classifier: Programming Language :: Python :: 3
